epiccore/__init__.py
epiccore/api_client.py
epiccore/configuration.py
epiccore/exceptions.py
epiccore/rest.py
epiccore/api/__init__.py
epiccore/api/billing_api.py
epiccore/api/catalog_api.py
epiccore/api/config_api.py
epiccore/api/data_api.py
epiccore/api/desktop_api.py
epiccore/api/job_api.py
epiccore/api/jobauth_api.py
epiccore/api/jobrefresh_api.py
epiccore/api/jobstep_api.py
epiccore/api/licenses_api.py
epiccore/api/profile_api.py
epiccore/api/projects_api.py
epiccore/api/teams_api.py
epiccore/models/__init__.py
epiccore/models/accelerator_config.py
epiccore/models/application.py
epiccore/models/application_configuration_serialiser.py
epiccore/models/batch_application_details.py
epiccore/models/batch_application_list.py
epiccore/models/batch_application_version_details.py
epiccore/models/batch_queue_details.py
epiccore/models/budget.py
epiccore/models/cluster_node_config.py
epiccore/models/cost.py
epiccore/models/cost_threshold.py
epiccore/models/current_spend.py
epiccore/models/data_location.py
epiccore/models/data_spec.py
epiccore/models/desktop_instance.py
epiccore/models/desktop_node_launch_spec.py
epiccore/models/desktop_node_quote.py
epiccore/models/desktop_node_type.py
epiccore/models/discount.py
epiccore/models/env_var.py
epiccore/models/env_var_template.py
epiccore/models/environment_variable.py
epiccore/models/file.py
epiccore/models/file_details.py
epiccore/models/folder.py
epiccore/models/folder_details.py
epiccore/models/iaas_cost.py
epiccore/models/inline_response200.py
epiccore/models/inline_response2001.py
epiccore/models/inline_response20010.py
epiccore/models/inline_response20011.py
epiccore/models/inline_response2002.py
epiccore/models/inline_response2003.py
epiccore/models/inline_response2004.py
epiccore/models/inline_response2005.py
epiccore/models/inline_response2006.py
epiccore/models/inline_response2007.py
epiccore/models/inline_response2008.py
epiccore/models/inline_response2009.py
epiccore/models/job.py
epiccore-0.0.28.dist-info/METADATA
epiccore-0.0.28.dist-info/WHEEL
epiccore-0.0.28.dist-info/top_level.txt
epiccore-0.0.28.dist-info/RECORD
