Metadata-Version: 2.1
Name: epiccore
Version: 0.0.28
Summary: "EPIC Core API"
Author: "Zenotech"
Author-email: "support@zenotech.com"
License: BSD 3-Clause License
Classifier: License :: OSI Approved :: BSD License
Classifier: Programming Language :: Python :: 3
Classifier: Programming Language :: Python :: 3.5
Classifier: Programming Language :: Python :: 3.6
Classifier: Programming Language :: Python :: 3.7
Requires-Dist: urllib3
Requires-Dist: six
Requires-Dist: certifi
Requires-Dist: python-dateutil
